tif/.gitignore
tif/__init__.py
tif/bin/__init__.py
tif/bin/magento.py
tif/cli/__init__.py
tif/cli/options.py
tif/composer/__init__.py
tif/composer/operations.py
tif/docker/__init__.py
tif/docker/magento.py
tif/docker/service.py
tif/docker/warden.py
tif/fabric/Colors.py
tif/fabric/CommandPrefix.py
tif/fabric/__init__.py
tif/fabric/cli.py
tif/fabric/logger.py
tif/files/__init__.py
tif/files/operations.py
tif/git/__init__.py
tif/git/operations.py
tif/sql/__init__.py
tif/sql/operations.py
tif-3.1.0.dist-info/METADATA
tif-3.1.0.dist-info/WHEEL
tif-3.1.0.dist-info/licenses/LICENSE
tif-3.1.0.dist-info/RECORD
